{"@type": "ItemList", "@context": {"@vocab": "http://schema.org/", "detailedDescription": "goog:detailedDescription", "resultScore": "goog:resultScore", "kg": "http://g.co/kg", "EntitySearchResult": "goog:EntitySearchResult", "goog": "http://schema.googleapis.com/"}, "itemListElement": [{"@type": "EntitySearchResult", "result": {"description": "French film actress", "@type": ["Person", "Thing"], "name": "Emmanuelle B\u00e9art", "detailedDescription": {"license": "https://en.wikipedia.org/wiki/Wikipedia:Text_of_Creative_Commons_Attribution-ShareAlike_3.0_Unported_License", "url": "https://en.wikipedia.org/wiki/Emmanuelle_B%C3%A9art", "articleBody": "Emmanuelle B\u00e9art is a French film actress, who has appeared in over 60 film and television productions since 1972. An eight-time C\u00e9sar Award nominee, she won the C\u00e9sar Award for Best Supporting Actress for the 1986 film Manon des Sources. "}, "image": {"url": "https://commons.wikimedia.org/wiki/File:Emmanuelle_B%C3%A9art_1_(2009).jpg", "contentUrl": "http://t0.gstatic.com/images?q=tbn:ANd9GcRVe9XFP-7hVtEXoj89YfjSgSe_5EaQKknXdQoczMyYgUFwvV0i"}, "@id": "kg:/m/016nhj"}, "resultScore": 20.327585}]}