{"@type": "ItemList", "@context": {"@vocab": "http://schema.org/", "detailedDescription": "goog:detailedDescription", "resultScore": "goog:resultScore", "kg": "http://g.co/kg", "EntitySearchResult": "goog:EntitySearchResult", "goog": "http://schema.googleapis.com/"}, "itemListElement": [{"@type": "EntitySearchResult", "result": {"description": "American artist", "@type": ["Person", "Thing"], "name": "Robert W. Chambers", "detailedDescription": {"license": "https://en.wikipedia.org/wiki/Wikipedia:Text_of_Creative_Commons_Attribution-ShareAlike_3.0_Unported_License", "url": "https://en.wikipedia.org/wiki/Robert_W._Chambers", "articleBody": "Robert William Chambers was an American artist and fiction writer, best known for his book of short stories entitled The King in Yellow, published in 1895."}, "image": {"url": "https://en.wikipedia.org/wiki/Robert_W._Chambers", "contentUrl": "http://t3.gstatic.com/images?q=tbn:ANd9GcSGULQW3i1mKWzmPGWugNK4VKfwnrXWJrh7i6SO6F4Mk-Kbj_38"}, "@id": "kg:/m/01b7r6"}, "resultScore": 14.554945}]}