{"@type": "ItemList", "@context": {"@vocab": "http://schema.org/", "detailedDescription": "goog:detailedDescription", "resultScore": "goog:resultScore", "kg": "http://g.co/kg", "EntitySearchResult": "goog:EntitySearchResult", "goog": "http://schema.googleapis.com/"}, "itemListElement": [{"@type": "EntitySearchResult", "result": {"url": "http://bettemidler.com/", "description": "American singer-songwriter", "@type": ["Person", "Thing"], "name": "Bette Midler", "detailedDescription": {"license": "https://en.wikipedia.org/wiki/Wikipedia:Text_of_Creative_Commons_Attribution-ShareAlike_3.0_Unported_License", "url": "https://en.wikipedia.org/wiki/Bette_Midler", "articleBody": "Bette Midler is an American singer, songwriter, actress, comedian, and film producer.\nBorn in Honolulu, Hawaii, Midler began her professional career in several Off-Off-Broadway plays, prior to her engagements in Fiddler on the Roof and Salvation on Broadway in the late 1960s. "}, "image": {"url": "https://hr.wikipedia.org/wiki/Bette_Midler", "contentUrl": "http://t3.gstatic.com/images?q=tbn:ANd9GcTyJSAhE8keLvfaAe1zAL3fzvkRTbWqwqzfQLssA3NKYUa8FZzf"}, "@id": "kg:/m/01dw9z"}, "resultScore": 25.10532}]}