{"@type": "ItemList", "@context": {"@vocab": "http://schema.org/", "detailedDescription": "goog:detailedDescription", "resultScore": "goog:resultScore", "kg": "http://g.co/kg", "EntitySearchResult": "goog:EntitySearchResult", "goog": "http://schema.googleapis.com/"}, "itemListElement": [{"@type": "EntitySearchResult", "result": {"description": "American geologist", "@type": ["Person", "Thing"], "name": "Eugene Merle Shoemaker", "detailedDescription": {"license": "https://en.wikipedia.org/wiki/Wikipedia:Text_of_Creative_Commons_Attribution-ShareAlike_3.0_Unported_License", "url": "https://en.wikipedia.org/wiki/Eugene_Merle_Shoemaker", "articleBody": "Eugene Merle Shoemaker, also known as Gene Shoemaker, was an American geologist and one of the founders of the field of planetary science. He is best known for co-discovering the Comet Shoemaker\u2013Levy 9 with his wife Carolyn S. Shoemaker and David H. Levy. This comet hit Jupiter in July 1994: the impact was televised around the world.\nShoemaker was also well known for his studies of terrestrial craters, such as Barringer Meteor Crater in Arizona. Shoemaker was the first scientist to conclude that these craters were caused by meteor impact. Shoemaker was also the first director of the United States Geological Survey's Astrogeology Research Program."}, "image": {"url": "https://en.wikipedia.org/wiki/Eugene_Merle_Shoemaker", "contentUrl": "http://t0.gstatic.com/images?q=tbn:ANd9GcSV7gfbS51_1ScQ3Su4XUv5t0xPHGXsu_LvsUxHg0ob3v5BD9ih"}, "@id": "kg:/m/01ktnp"}, "resultScore": 16.929119}]}