{"@type": "ItemList", "@context": {"@vocab": "http://schema.org/", "detailedDescription": "goog:detailedDescription", "resultScore": "goog:resultScore", "kg": "http://g.co/kg", "EntitySearchResult": "goog:EntitySearchResult", "goog": "http://schema.googleapis.com/"}, "itemListElement": [{"@type": "EntitySearchResult", "result": {"description": "Italian musician", "@type": ["Thing", "Person"], "name": "Renato Carosone", "detailedDescription": {"license": "https://en.wikipedia.org/wiki/Wikipedia:Text_of_Creative_Commons_Attribution-ShareAlike_3.0_Unported_License", "url": "https://en.wikipedia.org/wiki/Renato_Carosone", "articleBody": "Renato Carosone, born Renato Carusone, was an Italian musician. He was a prominent figure of the Italian music scene in the second half of the 20th century. He was also a modern performer of the so-called canzone napoletana, Naples' song tradition."}, "image": {"url": "https://commons.wikimedia.org/wiki/File:Renato_Carosone_-_fotografia_di_Augusto_De_Luca.jpg", "contentUrl": "http://t1.gstatic.com/images?q=tbn:ANd9GcRY7x2E_-cRp5gRBmmRkAzdHpspLts6MsSzToCgf6UP183fQ3ny"}, "@id": "kg:/m/01nkkz7"}, "resultScore": 17.147997}]}