{"@type": "ItemList", "@context": {"@vocab": "http://schema.org/", "detailedDescription": "goog:detailedDescription", "resultScore": "goog:resultScore", "kg": "http://g.co/kg", "EntitySearchResult": "goog:EntitySearchResult", "goog": "http://schema.googleapis.com/"}, "itemListElement": [{"@type": "EntitySearchResult", "result": {"url": "http://orikasa.chu.jp/", "description": "Japanese voice actress", "@type": ["Thing", "Person"], "name": "Ai Orikasa", "detailedDescription": {"license": "https://en.wikipedia.org/wiki/Wikipedia:Text_of_Creative_Commons_Attribution-ShareAlike_3.0_Unported_License", "url": "https://en.wikipedia.org/wiki/Ai_Orikasa", "articleBody": "Ai Orikasa is a Japanese voice actress and singer from Tokyo. She formerly worked for Production Baobab but left for AXL-ONE, Toshiyuki Morikawa's agency. Orikasa also provided the Japanese dub voice for Jessica Rabbit in Who Framed Roger Rabbit. Her debut work was Shoukoushi Cedie in 1988. She is best known for the roles of Pururun, Ryoko, and Quatre Raberba Winner."}, "@id": "kg:/m/01wpgmk"}, "resultScore": 16.428282}]}