{"itemListElement": [{"resultScore": 13.191956, "@type": "EntitySearchResult", "result": {"@type": ["Person", "Thing"], "detailedDescription": {"articleBody": "Colonel Richard Meinertzhagen, CBE, DSO was a British soldier, intelligence officer and ornithologist. He had a decorated military career spanning Africa, where he was credited with creating and executing the infamous Haversack Ruse. ", "url": "https://en.wikipedia.org/wiki/Richard_Meinertzhagen", "license": "https://en.wikipedia.org/wiki/Wikipedia:Text_of_Creative_Commons_Attribution-ShareAlike_3.0_Unported_License"}, "description": "British soldier", "name": "Richard Meinertzhagen", "@id": "kg:/m/02_x3m", "image": {"contentUrl": "http://t3.gstatic.com/images?q=tbn:ANd9GcRUOQUvxCTgf5W5OHxkAtFI75Tg1YmP0ZMiLg5GEjafJmRv5Pve", "url": "https://en.wikipedia.org/wiki/Richard_Meinertzhagen"}}}], "@context": {"resultScore": "goog:resultScore", "EntitySearchResult": "goog:EntitySearchResult", "kg": "http://g.co/kg", "@vocab": "http://schema.org/", "goog": "http://schema.googleapis.com/", "detailedDescription": "goog:detailedDescription"}, "@type": "ItemList"}