{"itemListElement": [{"resultScore": 18.053017, "@type": "EntitySearchResult", "result": {"@type": ["Person", "Thing"], "detailedDescription": {"articleBody": "Margaret Bourke-White was an American photographer and documentary photographer. She is best known as the first foreign photographer permitted to take pictures of the Soviet five-year plan, the first American female war photojournalist, and having one of her photographs on the cover of the first issue of Life magazine. ", "url": "https://en.wikipedia.org/wiki/Margaret_Bourke-White", "license": "https://en.wikipedia.org/wiki/Wikipedia:Text_of_Creative_Commons_Attribution-ShareAlike_3.0_Unported_License"}, "description": "American photographer", "name": "Margaret Bourke-White", "@id": "kg:/m/02grhl", "image": {"contentUrl": "http://t1.gstatic.com/images?q=tbn:ANd9GcQNItRvAMcTESo2OaNjhaedRLRBVoRNhYKNEiG6sEHEWmzQt9lN", "url": "https://commons.wikimedia.org/wiki/File:Margaret_Bourke-White_1955.jpg"}}}], "@context": {"resultScore": "goog:resultScore", "EntitySearchResult": "goog:EntitySearchResult", "kg": "http://g.co/kg", "@vocab": "http://schema.org/", "goog": "http://schema.googleapis.com/", "detailedDescription": "goog:detailedDescription"}, "@type": "ItemList"}