{"itemListElement": [{"resultScore": 14.910128, "@type": "EntitySearchResult", "result": {"@type": ["Person", "Thing"], "detailedDescription": {"articleBody": "Gary Russell Jr. is an American professional boxer. He has held the WBC featherweight title since 2015, and as an amateur he won a bronze medal in the bantamweight division at the 2005 World Championships. ", "url": "https://en.wikipedia.org/wiki/Gary_Russell_Jr.", "license": "https://en.wikipedia.org/wiki/Wikipedia:Text_of_Creative_Commons_Attribution-ShareAlike_3.0_Unported_License"}, "description": "American professional boxer", "name": "Gary Russell Jr.", "@id": "kg:/m/02q4mbb", "image": {"contentUrl": "http://t2.gstatic.com/images?q=tbn:ANd9GcTDi6OsFP1uwxOcUD8mgYQAVydfE4wveCJgROoqL1zdR_OZfeiP", "url": "https://en.wikipedia.org/wiki/Gary_Russell_Jr."}}}], "@context": {"resultScore": "goog:resultScore", "EntitySearchResult": "goog:EntitySearchResult", "kg": "http://g.co/kg", "@vocab": "http://schema.org/", "goog": "http://schema.googleapis.com/", "detailedDescription": "goog:detailedDescription"}, "@type": "ItemList"}