{"itemListElement": [{"resultScore": 12.223274, "@type": "EntitySearchResult", "result": {"@type": ["Person", "Thing"], "detailedDescription": {"articleBody": "Jean-Paul van Poppel is a former Dutch racing cyclist, who was nicknamed Popeye.\nVan Poppel was one of the most successful Dutch road sprinters. He won stages in mass sprints in all three Grand Tours, sometimes from positions that appeared lost. In the Tour de France he won 9 stages altogether. In 1988 he won 4 stages, the highest won number by a Dutch cyclist in one tour. He also competed in the individual road race event at the 1984 Summer Olympics.\nVan Poppel won the points classification in the 1987 Tour de France. After he ended his career in 1995, he became a directeur sportif in women's cycling. ", "url": "https://en.wikipedia.org/wiki/Jean-Paul_van_Poppel", "license": "https://en.wikipedia.org/wiki/Wikipedia:Text_of_Creative_Commons_Attribution-ShareAlike_3.0_Unported_License"}, "description": "Dutch cyclist", "name": "Jean-Paul van Poppel", "@id": "kg:/m/02qv8fn", "image": {"contentUrl": "http://t0.gstatic.com/images?q=tbn:ANd9GcQ7iVtpoReo2JuoSU-FEzs3HDxrhX9lVh1Z9xEasG1qKt_mzO0s", "url": "https://en.wikipedia.org/wiki/Jean-Paul_van_Poppel"}}}], "@context": {"resultScore": "goog:resultScore", "EntitySearchResult": "goog:EntitySearchResult", "kg": "http://g.co/kg", "@vocab": "http://schema.org/", "goog": "http://schema.googleapis.com/", "detailedDescription": "goog:detailedDescription"}, "@type": "ItemList"}