{"@context": {"resultScore": "goog:resultScore", "kg": "http://g.co/kg", "EntitySearchResult": "goog:EntitySearchResult", "goog": "http://schema.googleapis.com/", "@vocab": "http://schema.org/", "detailedDescription": "goog:detailedDescription"}, "@type": "ItemList", "itemListElement": [{"resultScore": 15.130005, "result": {"detailedDescription": {"license": "https://en.wikipedia.org/wiki/Wikipedia:Text_of_Creative_Commons_Attribution-ShareAlike_3.0_Unported_License", "articleBody": "Karen Malina White is an American film and television actress. White is best known for her roles as Kaneesha Carter, in the 1989 drama film Lean on Me, as Charmaine Brown during the two final seasons on The Cosby Show and its spin-off A Different World; Nicolette Vandross on Malcolm &amp; Eddie and the voice of Dijonay Jones on the Disney Channel animated comedy The Proud Family.", "url": "https://en.wikipedia.org/wiki/Karen_Malina_White"}, "@id": "kg:/m/034dgl", "description": "American film actress", "@type": ["Thing", "Person"], "name": "Karen Malina White"}, "@type": "EntitySearchResult"}]}