{"@context": {"resultScore": "goog:resultScore", "kg": "http://g.co/kg", "EntitySearchResult": "goog:EntitySearchResult", "goog": "http://schema.googleapis.com/", "@vocab": "http://schema.org/", "detailedDescription": "goog:detailedDescription"}, "@type": "ItemList", "itemListElement": [{"resultScore": 16.645355, "result": {"image": {"url": "https://en.wikipedia.org/wiki/Jan_Stenerud", "contentUrl": "http://t3.gstatic.com/images?q=tbn:ANd9GcRYlTM8Zfb1Cap99Ygie4bjE4vatwlz5cep0tVzXCXWOlTe4_mN"}, "detailedDescription": {"license": "https://en.wikipedia.org/wiki/Wikipedia:Text_of_Creative_Commons_Attribution-ShareAlike_3.0_Unported_License", "articleBody": "Jan Stenerud is a Norwegian former professional American football player for the AFL/NFL Kansas City Chiefs, Green Bay Packers, and Minnesota Vikings. He is the first pure placekicker to be inducted in the Pro Football Hall of Fame. Stenerud is distinguished as being the first Norwegian to play in the NFL.", "url": "https://en.wikipedia.org/wiki/Jan_Stenerud"}, "@id": "kg:/m/03lysn", "description": "Former football player", "@type": ["Person", "Thing"], "name": "Jan Stenerud"}, "@type": "EntitySearchResult"}]}