{"@context": {"resultScore": "goog:resultScore", "kg": "http://g.co/kg", "EntitySearchResult": "goog:EntitySearchResult", "goog": "http://schema.googleapis.com/", "@vocab": "http://schema.org/", "detailedDescription": "goog:detailedDescription"}, "@type": "ItemList", "itemListElement": [{"resultScore": 17.686136, "result": {"image": {"url": "https://en.wikipedia.org/wiki/Bianna_Golodryga", "contentUrl": "http://t3.gstatic.com/images?q=tbn:ANd9GcQixpO9Ntn_EsfiEc1FxB4Y5hhPeyy3P6Tw_mayJ_AmF-__B2Q9"}, "detailedDescription": {"license": "https://en.wikipedia.org/wiki/Wikipedia:Text_of_Creative_Commons_Attribution-ShareAlike_3.0_Unported_License", "articleBody": "Bianna Vitalievna Golodryga is an American journalist who is currently serving as a co-host of CBS This Morning and a contributor on CNN. She was previously the news and finance anchor at Yahoo! News. She was also previously co-anchor of the weekend edition of ABC's Good Morning America.", "url": "https://en.wikipedia.org/wiki/Bianna_Golodryga"}, "@id": "kg:/m/03y9mm9", "description": "Journalist", "@type": ["Thing", "Person"], "name": "Bianna Golodryga"}, "@type": "EntitySearchResult"}]}