{"itemListElement": [{"resultScore": 16.515568, "result": {"@id": "kg:/m/05n3hp", "name": "Ilir Meta", "description": "President of Albania", "image": {"contentUrl": "http://t2.gstatic.com/images?q=tbn:ANd9GcQEbpjbxHJANcuas8CZnDUByGXHE1Ez_a7HmeRLSttAK9N4qcYN", "url": "https://commons.wikimedia.org/wiki/File:Ilir_Meta_detail,_000824-D-9880W-002.jpg"}, "detailedDescription": {"license": "https://en.wikipedia.org/wiki/Wikipedia:Text_of_Creative_Commons_Attribution-ShareAlike_3.0_Unported_License", "articleBody": "Ilir Meta is an Albanian diplomat and politician who has been serving as President of Albania since 24 July 2017. Previously he served as Prime Minister from 1999 to 2002, and at age 30 he is to date the youngest person to have been Prime Minister in Albanian history. ", "url": "https://en.wikipedia.org/wiki/Ilir_Meta"}, "@type": ["Person", "Thing"]}, "@type": "EntitySearchResult"}], "@type": "ItemList", "@context": {"goog": "http://schema.googleapis.com/", "resultScore": "goog:resultScore", "@vocab": "http://schema.org/", "EntitySearchResult": "goog:EntitySearchResult", "kg": "http://g.co/kg", "detailedDescription": "goog:detailedDescription"}}