{"@type": "ItemList", "@context": {"goog": "http://schema.googleapis.com/", "detailedDescription": "goog:detailedDescription", "EntitySearchResult": "goog:EntitySearchResult", "@vocab": "http://schema.org/", "resultScore": "goog:resultScore", "kg": "http://g.co/kg"}, "itemListElement": [{"resultScore": 20.138836, "result": {"detailedDescription": {"license": "https://en.wikipedia.org/wiki/Wikipedia:Text_of_Creative_Commons_Attribution-ShareAlike_3.0_Unported_License", "articleBody": "Ram\u00f3n \u00c1ngel D\u00edaz is a former Argentine footballer and manager. He played for River Plate as a striker, and coached it for three tenures, winning eight titles. He is also known by the nickname of El Pelado.", "url": "https://en.wikipedia.org/wiki/Ram%C3%B3n_D%C3%ADaz"}, "@id": "kg:/m/08gqcf", "@type": ["Thing", "Person"], "description": "Argentine soccer player", "image": {"contentUrl": "http://t3.gstatic.com/images?q=tbn:ANd9GcS-ev3d5rhXi8FrDTroeMOSuj1dRBpXlDmEjCnEvKIO9qgxNepV", "url": "https://en.wikipedia.org/wiki/Ram%C3%B3n_D%C3%ADaz"}, "name": "Ram\u00f3n D\u00edaz"}, "@type": "EntitySearchResult"}]}