{"@type": "ItemList", "@context": {"goog": "http://schema.googleapis.com/", "detailedDescription": "goog:detailedDescription", "EntitySearchResult": "goog:EntitySearchResult", "@vocab": "http://schema.org/", "resultScore": "goog:resultScore", "kg": "http://g.co/kg"}, "itemListElement": [{"resultScore": 13.177185, "result": {"detailedDescription": {"license": "https://en.wikipedia.org/wiki/Wikipedia:Text_of_Creative_Commons_Attribution-ShareAlike_3.0_Unported_License", "articleBody": "Emmanuel \"Manno\" Sanon was a Haitian footballer who played as a striker. He starred in the Haiti national football team winning the 1973 CONCACAF Championship and scored the team's only two goals in its history during the 1974 FIFA World Cup in West Germany, where he became notorious for snapping Italy's Dino Zoff's no-goal 1,142-minute streak from a lead pass from Philippe Vorbe.\n", "url": "https://en.wikipedia.org/wiki/Emmanuel_Sanon"}, "@id": "kg:/m/08lw0s", "name": "Emmanuel Sanon", "description": "Haitian soccer player", "@type": ["Person", "Thing"]}, "@type": "EntitySearchResult"}]}