{"@type": "ItemList", "@context": {"goog": "http://schema.googleapis.com/", "detailedDescription": "goog:detailedDescription", "EntitySearchResult": "goog:EntitySearchResult", "@vocab": "http://schema.org/", "resultScore": "goog:resultScore", "kg": "http://g.co/kg"}, "itemListElement": [{"resultScore": 14.362513, "result": {"detailedDescription": {"license": "https://en.wikipedia.org/wiki/Wikipedia:Text_of_Creative_Commons_Attribution-ShareAlike_3.0_Unported_License", "articleBody": "Fred Bear was an American bow hunter, bow manufacturer, author, and television host.\nHe was born in the town of Waynesboro, Pennsylvania. ", "url": "https://en.wikipedia.org/wiki/Fred_Bear"}, "@id": "kg:/m/08rt7f", "@type": ["Thing", "Person"], "description": "American bow manufacturer", "image": {"contentUrl": "http://t2.gstatic.com/images?q=tbn:ANd9GcSCOFpBof-mWFSrPJYgwfA6lrziIj-nI-ehUabQijD1mAADfB8R", "url": "https://commons.wikimedia.org/wiki/File:Fred_Bear_and_Jim_Henderson_moose_hunt_1943.jpg"}, "name": "Fred Bear"}, "@type": "EntitySearchResult"}]}