{"itemListElement": [{"resultScore": 16.426203, "result": {"@id": "kg:/m/0smljg5", "description": "Japanese voice actress", "name": "Sora Tokui", "@type": ["Thing", "Person"], "image": {"contentUrl": "http://t2.gstatic.com/images?q=tbn:ANd9GcRvvETfzRVBXP8sAO6bHIUJouoITwDdZKHvgrXea5mGcWnuza66", "url": "https://en.wikipedia.org/wiki/Sora_Tokui"}, "detailedDescription": {"license": "https://en.wikipedia.org/wiki/Wikipedia:Text_of_Creative_Commons_Attribution-ShareAlike_3.0_Unported_License", "articleBody": "Sora Tokui is a Japanese voice actress, singer and manga artist who made her debut as a voice actress in 2009 as Himemiya in Wei\u00df Survive R.\n", "url": "https://en.wikipedia.org/wiki/Sora_Tokui"}}, "@type": "EntitySearchResult"}], "@context": {"@vocab": "http://schema.org/", "resultScore": "goog:resultScore", "detailedDescription": "goog:detailedDescription", "kg": "http://g.co/kg", "goog": "http://schema.googleapis.com/", "EntitySearchResult": "goog:EntitySearchResult"}, "@type": "ItemList"}